Workbook

Sheet Resumen
B2: Propuesta Financiera de Consultoría
B3: Plataforma Analítica de Mortalidad End to End
B4: Seminario de Sistemas 2, Sección A — Escuela de Vacaciones 2026
B6: Modalidad de contratación | C6: Suma alzada (lump sum), pagos asociados a hitos de entrega, bajo el esquema de honorario todo incluido aplicado por el PNUD a sus contratos individuales (UNDP, 2025)
B7: Duración del proyecto | C7: 4 meses calendario, conforme al Project Charter del proyecto
B8: Tipo de cambio aplicado | C8: 7.66 | D8: Fuente: Living in Guatemala (2026), tipo de cambio del 8 de marzo de 2026.
B10: Resumen de costos
B11: Componente | C11: Monto (USD)
B12: Costo de personal | C12: ='Costos de Personal'!I10 -> 19265.609
B13: Costo no personal (nube y licencias) | C13: ='Costos No Personal'!E9 -> 1012.6
B14: Costo total del proyecto (suma alzada) | C14: =C12+C13 -> 20278.209
B17: Composición del equipo
B18: Rol | C18: Persona-mes asignados | D18: Tarifa mensual (USD)
B19: Ingeniero de Datos | C19: ='Costos de Personal'!G6 -> 3 | D19: ='Tarifas y Fuentes'!E6 -> 3490.9051
B20: Gerente de Proyecto | C20: ='Costos de Personal'!G7 -> 1.5 | D20: ='Tarifas y Fuentes'!E7 -> 2859.4865
B21: Científico de Datos | C21: ='Costos de Personal'!G8 -> 1 | D21: ='Tarifas y Fuentes'!E8 -> 2820.1044
B22: Analista de Datos / Desarrollador BI | C22: ='Costos de Personal'!G9 -> 0.75 | D22: ='Tarifas y Fuentes'!E9 -> 2244.7454
B24: Nota metodológica: las tarifas de personal se basan en datos de mercado verificados para Guatemala (ERI SalaryExpert, 2026), consistente con el principio Flemming de la Comisión de Administración Pública Internacional, según el cual el personal contratado localmente se remunera con base en encuestas del mercado laboral local y no en la escala internacional (ICSC; UN Policy Portal, s.f.). La hoja 'Tarifas y Fuentes' presenta la escala de honorarios de consultores internacionales de Naciones Unidas únicamente como referencia comparativa, no como base de cálculo.

Sheet Tarifas y Fuentes
B2: Benchmarking de Tarifas por Rol
B3: Mercado laboral de Guatemala, datos verificados a 2026
B5: Rol | C5: Salario anual promedio (GTQ) | D5: Salario anual promedio (USD) | E5: Tarifa mensual (USD) | F5: Tarifa mensual usada (USD) | G5: Fuente
B6: Ingeniero de Datos | C6: 320884 | D6: =C6/Resumen!C8 -> 41890.862 | E6: =D6/12 -> 3490.9051 | F6: =E6 -> 3490.9051 | G6: ERI SalaryExpert (2026). Computer Software Engineer Salary in Guatemala. Recuperado de salaryexpert.com. Se usa como referente directo de Ingeniero de Datos al no existir una serie nacional separada para esa denominacion especifica en la base de ERI para Guatemala; ambos roles comparten el mismo perfil de formacion y herramientas (programacion, bases de datos, arquitectura de software).
B7: Gerente de Proyecto | C7: 262844 | D7: =C7/Resumen!C8 -> 34313.838 | E7: =D7/12 -> 2859.4865 | F7: =E7 -> 2859.4865 | G7: ERI SalaryExpert (2026). Program Project Manager Salary in Guatemala City, Guatemala. Recuperado de salaryexpert.com.
B8: Cientifico de Datos | C8: 259224 | D8: =C8/Resumen!C8 -> 33841.253 | E8: =D8/12 -> 2820.1044 | F8: =E8 -> 2820.1044 | G8: ERI SalaryExpert (2026). Data Scientist Salary in Guatemala City, Guatemala. Recuperado de salaryexpert.com.
B9: Analista de Datos / Desarrollador BI | C9: 206337 | D9: =C9/Resumen!C8 -> 26936.945 | E9: =D9/12 -> 2244.7454 | F9: =E9 -> 2244.7454 | G9: ERI SalaryExpert (2026). Data Analyst Salary in Guatemala. Recuperado de salaryexpert.com.
B11: Referencia comparativa: escala de honorarios de consultores internacionales de la ONU
B12: Nivel | C12: Tarifa diaria minima (USD) | D12: Tarifa diaria maxima (USD) | E12: Tarifa mensual minima (USD) | F12: Tarifa mensual maxima (USD) | G12: Fuente
B13: A | C13: 190 | D13: 260 | E13: 3956 | F13: 5492 | G13: United Nations Office of Human Resources (2025). Policy Guideline OHR/PG/2025/2: Fee ranges for international consultants and individual contractors, 17 de enero de 2025. policy.un.org. Esta misma fuente respalda los 5 niveles (A a E) de esta tabla.
B14: B | C14: 270 | D14: 420 | E14: 5140 | F14: 8727
B15: C | C15: 430 | D15: 650 | E15: 8095 | F15: 12399
B16: D | C16: 660 | D16: 890 | E16: 11491 | F16: 15503
B17: E | C17: 1000 | D17: 1100 | E17: 16090 | F17: 17719
B19: Esta escala corresponde a consultores internacionales desplegados fuera de su pais de residencia, con compensacion que incorpora viaticos, dificultad y reubicacion. Las tarifas de este proyecto, calculadas para personal contratado localmente en Guatemala, son consistentes con el principio Flemming de la Comision de Administracion Publica Internacional (ICSC), que exige remunerar al personal local con base en el mercado laboral de la sede de trabajo y no en la escala internacional (UN Policy Portal, s.f.). Por esa razon, las tarifas locales utilizadas en esta propuesta se ubican por debajo del nivel A de la escala internacional, lo cual es metodologicamente correcto y no representa una subestimacion del valor del trabajo realizado.

Sheet Costos de Personal
B2: Costos de Personal por Rol y Mes
B3: Asignacion en persona-mes (FTE) sobre los 4 meses del proyecto
B5: Rol | C5: Mes 1 (FTE) | D5: Mes 2 (FTE) | E5: Mes 3 (FTE) | F5: Mes 4 (FTE) | G5: Total persona-mes | H5: Tarifa mensual (USD) | I5: Costo total (USD)
B6: Ingeniero de Datos | C6: 1 | D6: 1.5 | E6: 0.25 | F6: 0.25 | G6: =SUM(C6:F6) -> 3 | H6: ='Tarifas y Fuentes'!E6 -> 3490.9051 | I6: =G6*H6 -> 10472.715
B7: Gerente de Proyecto | C7: 0.25 | D7: 0.25 | E7: 0.25 | F7: 0.75 | G7: =SUM(C7:F7) -> 1.5 | H7: ='Tarifas y Fuentes'!E7 -> 2859.4865 | I7: =G7*H7 -> 4289.2298
B8: Cientifico de Datos | C8: 0 | D8: 0 | E8: 0.75 | F8: 0.25 | G8: =SUM(C8:F8) -> 1 | H8: ='Tarifas y Fuentes'!E8 -> 2820.1044 | I8: =G8*H8 -> 2820.1044
B9: Analista de Datos / Desarrollador BI | C9: 0 | D9: 0 | E9: 0.5 | F9: 0.25 | G9: =SUM(C9:F9) -> 0.75 | H9: ='Tarifas y Fuentes'!E9 -> 2244.7454 | I9: =G9*H9 -> 1683.5591
B10: Total | C10: =SUM(C6:C9) -> 1.25 | D10: =SUM(D6:D9) -> 1.75 | E10: =SUM(E6:E9) -> 1.75 | F10: =SUM(F6:F9) -> 1.5 | G10: =SUM(G6:G9) -> 6.25 | I10: =SUM(I6:I9) -> 19265.609
B12: La asignacion de persona-mes por rol y mes refleja la intensidad de cada fase del proyecto segun el cronograma del Project Charter: el mes 1 concentra la ingesta y arquitectura de datos (Fase 1); el mes 2 concentra la transformacion y el modelado dimensional (Fase 2), con apoyo adicional de ingenieria de datos para el sistema de respaldo; los meses 3 y 4 concentran el aprendizaje automatico, la visualizacion analitica y el cierre de la consultoria con el informe final (Fase 3). La gerencia de proyecto mantiene una asignacion continua y se intensifica en el cierre para la elaboracion del informe final y la gestion de la defensa.

Sheet Costos No Personal
B2: Costos No Personal (Nube y Licencias)
B3: Estimacion para 4 meses de proyecto, tarifas verificadas a 2026
B5: Concepto | C5: Tarifa unitaria (USD) | D5: Consumo mensual estimado | E5: Costo total 4 meses (USD) | F5: Fuente y supuesto de estimacion
B6: Databricks SQL Serverless (DBU) | C6: 0.7 | D6: 300 | E6: =C6*D6*4 -> 840 | F6: Tarifa verificada en Databricks (2026), Databricks Lakehouse Pricing, databricks.com/product/pricing/databricks-sql, USD 0.70 por DBU para SQL Serverless en regiones de EE.UU. El consumo mensual de 300 DBU es un supuesto de estimacion propio, basado en cargas intermitentes de transformacion ETL y consultas analiticas tipicas de un equipo de este tamano, no en una medicion de facturacion real.
B7: AWS S3 Standard Storage (GB-mes) | C7: 0.023 | D7: 50 | E7: =C7*D7*4 -> 4.6 | F7: Tarifa verificada en Amazon Web Services (2026), Amazon S3 Pricing, aws.amazon.com/s3/pricing, USD 0.023 por GB-mes para S3 Standard en la region us-east-1 (primeros 50 TB). El volumen de 50 GB es un supuesto de estimacion propio que cubre los archivos crudos, los respaldos en Parquet y la replica de auditoria del proyecto, con margen amplio sobre el volumen real observado.
B8: Microsoft Power BI Pro (licencia por usuario) | C8: 14 | D8: 3 | E8: =C8*D8*4 -> 168 | F8: Tarifa oficial vigente de Microsoft (2026), Power BI Pricing, microsoft.com/en-us/power-platform/products/power-bi/pricing, USD 14.00 por usuario al mes, vigente desde abril de 2025. Se asume una licencia por cada uno de los 3 integrantes del equipo durante los 4 meses del proyecto.
B9: Total costo no personal (4 meses) | E9: =SUM(E6:E8) -> 1012.6

Sheet Cronograma de Pagos
B2: Cronograma de Pagos por Hito
B3: Desembolsos asociados a los hitos del Project Charter
B5: Hito | C5: Entregable asociado | D5: Porcentaje del total | E5: Monto (USD)
B6: Hito 1 | C6: Entrega y defensa de la Fase 1: Fundamentos de Datos | D6: 0.2 | E6: =D6*Resumen!C14 -> 4055.6417
B7: Hito 2 | C7: Entrega y defensa de la Fase 2: Transformacion y Almacenamiento | D7: 0.25 | E7: =D7*Resumen!C14 -> 5069.5522
B8: Hito 3 | C8: Tarea complementaria de integraciones con herramientas de procesamiento | D8: 0.05 | E8: =D8*Resumen!C14 -> 1013.9104
B9: Hito 4 | C9: Entrega y defensa de la Fase 3: Aprendizaje Automatico y Business Intelligence | D9: 0.35 | E9: =D9*Resumen!C14 -> 7097.373
B10: Hito 5 | C10: Entrega del informe final de consultoria y cierre del proyecto | D10: 0.15 | E10: =D10*Resumen!C14 -> 3041.7313
B11: Total | D11: =SUM(D6:D10) -> 1 | E11: =SUM(E6:E10) -> 20278.209
B13: El esquema de pago contra hitos, en lugar de pago periodico fijo, es consistente con el modelo de contratacion por producto (output-based) que aplica el PNUD a sus contratos individuales, en el cual el pago se libera contra la entrega y aceptacion satisfactoria de cada producto, no contra el tiempo transcurrido (UNDP, 2025; UN Policy Portal, s.f.).

Sheet Referencias
B2: Referencias
B4: Amazon Web Services. (2026). Amazon S3 pricing. aws.amazon.com/s3/pricing
B5: Databricks. (2026). Databricks Lakehouse pricing. databricks.com/product/pricing/databricks-sql
B6: ERI SalaryExpert. (2026). Computer Software Engineer Salary in Guatemala. salaryexpert.com/salary/job/computer-software-engineer/guatemala
B7: ERI SalaryExpert. (2026). Data Analyst Salary in Guatemala. salaryexpert.com/salary/job/data-analyst/guatemala
B8: ERI SalaryExpert. (2026). Data Scientist Salary in Guatemala City, Guatemala. salaryexpert.com/salary/job/data-scientist/guatemala/guatemala-city
B9: ERI SalaryExpert. (2026). Program Project Manager Salary in Guatemala City, Guatemala. salaryexpert.com/salary/job/program-project-manager/guatemala/guatemala-city
B10: Living in Guatemala. (2026). Salarios Guatemala 2026: Q3,612 minimo + 20 profesiones. livinginguatemala.com/es/salarios
B11: Microsoft. (2026). Power BI pricing. microsoft.com/en-us/power-platform/products/power-bi/pricing
B12: United Nations Office of Human Resources. (2025). Policy Guideline OHR/PG/2025/2: Fee ranges for international consultants and individual contractors. policy.un.org
B13: UN Policy Portal. (s.f.). Consultants and individual contractors. policy.un.org/en/human-resources/other-personnel/consultants-and-individual-contractors
B14: United Nations Development Programme. (2025). Individual Contract. popp.undp.org/policy-page/individual-contract
